Metadata-Version: 1.1
Name: s3simplebackup
Version: 1.2.0
Summary: Backs up a file or directory to S3
Home-page: https://github.com/aDrongo/s3simplebackup/
Author: Ben Gardner
Author-email: bgardner160@gmail.com
License: UNKNOWN
Download-URL: https://github.com/aDrongo/s3simplebackup/archive/1.2.tar.gz
Platform: UNKNOWN
